gym_panfoo/__init__.py
gym_panfoo/envs/__init__.py
gym_panfoo/envs/panda_env.py
gym_panfoo-0.0.5.dist-info/METADATA
gym_panfoo-0.0.5.dist-info/WHEEL
gym_panfoo-0.0.5.dist-info/top_level.txt
gym_panfoo-0.0.5.dist-info/RECORD
