Metadata-Version: 2.1
Name: gym-panfoo
Version: 0.0.5
Summary: A OpenAI Gym Env for foo
Home-page: UNKNOWN
License: UNKNOWN
Platform: UNKNOWN
Requires-Dist: gym
